WinstonDoc/WinstonDoc.py
WinstonDoc/__init__.py
WinstonDoc/__main__.py
WinstonDoc/utils/__init__.py
WinstonDoc/utils/batch_file_loader.py
WinstonDoc/utils/embeddings.py
WinstonDoc/utils/errors.py
WinstonDoc/utils/flags.py
WinstonDoc/utils/interact.py
WinstonDoc/utils/llm.py
WinstonDoc/utils/loaders.py
WinstonDoc/utils/logger.py
WinstonDoc/utils/misc.py
WinstonDoc/utils/prompts.py
WinstonDoc/utils/retrievers.py
WinstonDoc/utils/typechecker.py
DocToolsLLM-0.99.0.dist-info/LICENSE.md
DocToolsLLM-0.99.0.dist-info/METADATA
DocToolsLLM-0.99.0.dist-info/WHEEL
DocToolsLLM-0.99.0.dist-info/entry_points.txt
DocToolsLLM-0.99.0.dist-info/top_level.txt
DocToolsLLM-0.99.0.dist-info/RECORD
