Metadata-Version: 2.1
Name: DocToolsLLM
Version: 0.99.0
Summary: (Now winston_doc) A perfect AI powered RAG for document query and summary. Supports ~all LLM and ~all filetypes (url, pdf, epub, youtube (incl playlist), audio, anki, md, docx, pptx, oe any combination!)
Home-page: https://github.com/thiswillbeyourgithub/WinstonDoc/
License: GPLv3
Keywords: RAG,search,summary,summarize,pdf,documents,doc,docx,youtube,mp3,embeddings,AI,LLM,openai,logseq,doctools,doctoolsllm,winston_doc
Classifier: Programming Language :: Python :: 3
Classifier: License :: OSI Approved :: GNU General Public License v3 (GPLv3)
Classifier: Operating System :: OS Independent
Requires-Python: >=3.10
License-File: LICENSE.md
Requires-Dist: wdoc
